multienginesearch/__init__.py
multienginesearch/cli.py
multienginesearch/engines.py
multienginesearch-0.1.0.dist-info/METADATA
multienginesearch-0.1.0.dist-info/WHEEL
multienginesearch-0.1.0.dist-info/entry_points.txt
multienginesearch-0.1.0.dist-info/RECORD
