Metadata-Version: 2.3
Name: multienginesearch
Version: 0.1.0
Summary: Multi-Engine Search - 多引擎搜索工具
Author: Maxiee
Author-email: maxieewong@gmail.com
Requires-Python: >=3.13
Classifier: Programming Language :: Python :: 3
Classifier: Programming Language :: Python :: 3.13
Requires-Dist: duckduckgo-search (>=6.0.0)
Requires-Dist: requests (>=2.31.0)
Requires-Dist: typer[all] (>=0.16.0,<0.17.0)
